<annotation>
	<folder>images</folder>
	<filename>none-img960.jpg</filename>
	<path>/Users/ggcstaff/CarND/CarND-Term3/models/research/images/none-img960.jpg</path>
	<source>
		<database>Unknown</database>
	</source>
	<size>
		<width>800</width>
		<height>600</height>
		<depth>3</depth>
	</size>
	<segmented>0</segmented>
	<object>
		<name>red</name>
		<pose>Unspecified</pose>
		<truncated>0</truncated>
		<difficult>0</difficult>
		<bndbox>
			<xmin>99</xmin>
			<ymin>544</ymin>
			<xmax>111</xmax>
			<ymax>570</ymax>
		</bndbox>
	</object>
	<object>
		<name>red</name>
		<pose>Unspecified</pose>
		<truncated>0</truncated>
		<difficult>0</difficult>
		<bndbox>
			<xmin>51</xmin>
			<ymin>543</ymin>
			<xmax>65</xmax>
			<ymax>568</ymax>
		</bndbox>
	</object>
	<object>
		<name>red</name>
		<pose>Unspecified</pose>
		<truncated>0</truncated>
		<difficult>0</difficult>
		<bndbox>
			<xmin>5</xmin>
			<ymin>540</ymin>
			<xmax>17</xmax>
			<ymax>565</ymax>
		</bndbox>
	</object>
</annotation>
